minknow_api/__init__.py
minknow_api/_support.py
minknow_api/_version.py
minknow_api/acquisition_pb2.py
minknow_api/acquisition_pb2_grpc.py
minknow_api/acquisition_service.py
minknow_api/analysis_configuration_pb2.py
minknow_api/analysis_configuration_pb2_grpc.py
minknow_api/analysis_configuration_service.py
minknow_api/analysis_workflows_pb2.py
minknow_api/analysis_workflows_pb2_grpc.py
minknow_api/analysis_workflows_service.py
minknow_api/basecaller_pb2.py
minknow_api/basecaller_pb2_grpc.py
minknow_api/basecaller_service.py
minknow_api/data.py
minknow_api/data_pb2.py
minknow_api/data_pb2_grpc.py
minknow_api/data_service.py
minknow_api/debug_pb2.py
minknow_api/debug_pb2_grpc.py
minknow_api/debug_service.py
minknow_api/device.py
minknow_api/device_pb2.py
minknow_api/device_pb2_grpc.py
minknow_api/device_service.py
minknow_api/hardware_check_pb2.py
minknow_api/hardware_check_pb2_grpc.py
minknow_api/hardware_check_service.py
minknow_api/instance_pb2.py
minknow_api/instance_pb2_grpc.py
minknow_api/instance_service.py
minknow_api/keystore_pb2.py
minknow_api/keystore_pb2_grpc.py
minknow_api/keystore_service.py
minknow_api/log_pb2.py
minknow_api/log_pb2_grpc.py
minknow_api/log_service.py
minknow_api/manager.py
minknow_api/manager_pb2.py
minknow_api/manager_pb2_grpc.py
minknow_api/manager_service.py
minknow_api/minion_device_pb2.py
minknow_api/minion_device_pb2_grpc.py
minknow_api/minion_device_service.py
minknow_api/pebble_device_pb2.py
minknow_api/pebble_device_pb2_grpc.py
minknow_api/pebble_device_service.py
minknow_api/post_processing_protocol_connection.py
minknow_api/promethion_device_pb2.py
minknow_api/promethion_device_pb2_grpc.py
minknow_api/promethion_device_service.py
minknow_api/protocol_pb2.py
minknow_api/protocol_pb2_grpc.py
minknow_api/protocol_service.py
minknow_api/protocol_settings_pb2.py
minknow_api/protocol_settings_pb2_grpc.py
minknow_api/protocol_settings_service.py
minknow_api/read_end_reason_pb2.py
minknow_api/read_end_reason_pb2_grpc.py
minknow_api-6.5.2.dist-info/METADATA
minknow_api-6.5.2.dist-info/WHEEL
minknow_api-6.5.2.dist-info/top_level.txt
minknow_api-6.5.2.dist-info/RECORD
