Metadata-Version: 2.4
Name: minknow_api
Version: 6.5.2
Summary: MinKNOW RPC API bindings
Home-page: https://github.com/nanoporetech/minknow_api
Author: Oxford Nanopore Technologies PLC
Author-email: info@nanoporetech.com
Requires-Dist: importlib-resources<3.3; python_version < "3.7.0"
Requires-Dist: grpcio~=1.51
Requires-Dist: numpy~=1.21
Requires-Dist: protobuf~=4.21
Requires-Dist: packaging>=15.0
Requires-Dist: pyrfc3339~=1.1
Dynamic: author
Dynamic: author-email
Dynamic: description
Dynamic: description-content-type
Dynamic: home-page
Dynamic: requires-dist
Dynamic: summary
